butext/__init__.py
butext/main.py
butext-0.3.6.dist-info/licenses/LICENSE
butext-0.3.6.dist-info/METADATA
butext-0.3.6.dist-info/WHEEL
butext-0.3.6.dist-info/top_level.txt
butext-0.3.6.dist-info/RECORD
