Metadata-Version: 2.4
Name: butext
Version: 0.3.6
Summary: https://butext.readthedocs.io/en/latest/
License-File: LICENSE
Requires-Dist: pandas
Requires-Dist: numpy
Requires-Dist: scikit-learn
Dynamic: description
Dynamic: license-file
Dynamic: requires-dist
Dynamic: summary
